models/label.py
models/models.py
models/project.py
models/task.py
models/team.py
models/user.py
models/enum/repeat_mode.py
models/enum/task_priority.py
py_vikunja-0.2.dist-info/LICENSE
py_vikunja-0.2.dist-info/METADATA
py_vikunja-0.2.dist-info/WHEEL
py_vikunja-0.2.dist-info/top_level.txt
py_vikunja-0.2.dist-info/RECORD
