Metadata-Version: 2.2
Name: py-vikunja
Version: 0.2
Summary: A Python wrapper for Vikunja API
Author: Joseph Shufflebotham
License: AGPL
License-File: LICENSE
Requires-Dist: httpx==0.28.1
